kasten/__init__.py
kasten/main.py
kasten/types.py
kasten/exceptions/__init__.py
kasten/generator/__init__.py
kasten/generator/pack.py
kasten-3.0.0.dist-info/LICENSE
kasten-3.0.0.dist-info/METADATA
kasten-3.0.0.dist-info/WHEEL
kasten-3.0.0.dist-info/top_level.txt
kasten-3.0.0.dist-info/RECORD
