Metadata-Version: 2.1
Name: kasten
Version: 3.0.0
Summary: Efficient, secure data serialization format with extensibility.
Home-page: https://git.voidnet.tech/kev/kasten
Author: Kevin Froman
Author-email: beardog@mailbox.org
License: UNKNOWN
Platform: UNKNOWN
Classifier: Programming Language :: Python :: 3
Classifier: License :: OSI Approved :: GNU General Public License v3 or later (GPLv3+)
Classifier: Operating System :: OS Independent
Classifier: Intended Audience :: Developers
Requires-Python: >3.6.0
Requires-Dist: msgpack
Requires-Dist: mimcvdf (>=1.2.0)
